shellserver/__init__.py
shellserver/__main__.py
shellserver/cli.py
shellserver/server.py
shellserver/style.py
shellserver/utils.py
shellserver/gitstatus/__init__.py
shellserver/gitstatus/base.py
shellserver/gitstatus/high.py
shellserver/gitstatus/interface.py
shellserver/gitstatus/packs.py
shellserver/gitstatus/plugins.py
shellserver/gitstatus/utils.py
shellserver-0.1.1.dist-info/METADATA
shellserver-0.1.1.dist-info/WHEEL
shellserver-0.1.1.dist-info/entry_points.txt
shellserver-0.1.1.dist-info/top_level.txt
shellserver-0.1.1.dist-info/RECORD
